slack_hero/__init__.py
slack_hero/log.py
slack_hero-0.2.dist-info/LICENSE
slack_hero-0.2.dist-info/METADATA
slack_hero-0.2.dist-info/WHEEL
slack_hero-0.2.dist-info/top_level.txt
slack_hero-0.2.dist-info/RECORD
