Metadata-Version: 2.1
Name: slack-hero
Version: 0.2
Summary: A package that enables you to easily send exception messages from django to slack
Requires-Python: >=3.6
License-File: LICENSE
Requires-Dist: slack-sdk (>=3.13.0)
